lsorm/__init__.py
lsorm/models.py
lsorm-0.0.2.dist-info/LICENSE
lsorm-0.0.2.dist-info/METADATA
lsorm-0.0.2.dist-info/WHEEL
lsorm-0.0.2.dist-info/RECORD
